aiotapioca/__init__.py
aiotapioca/__version__.py
aiotapioca/adapters/__init__.py
aiotapioca/adapters/adapters.py
aiotapioca/adapters/mixins.py
aiotapioca/client/__init__.py
aiotapioca/client/base.py
aiotapioca/client/client.py
aiotapioca/client/process_data.py
aiotapioca/exceptions.py
aiotapioca/generate.py
aiotapioca/py.typed
aiotapioca/serializers.py
aiotapioca/utils.py
aiotapioca_wrapper-4.3.0.dist-info/WHEEL
aiotapioca_wrapper-4.3.0.dist-info/METADATA
aiotapioca_wrapper-4.3.0.dist-info/licenses/LICENSE
aiotapioca_wrapper-4.3.0.dist-info/RECORD
