Metadata-Version: 2.1
Name: aiotapioca-wrapper
Version: 4.3.0
Summary: Python asynchronous I/O API client generator
License: MIT
Keywords: async,asyncio,tapioca,wrapper,api
Author-email: Filipe Ximenes <filipeximenes@gmail.com>,Andrey Ilin <andreyilin@fastmail.com>
Requires-Python: >=3.8
Classifier: Development Status :: 5 - Production/Stable
Classifier: Intended Audience :: Developers
Classifier: License :: OSI Approved :: MIT License
Classifier: Programming Language :: Python
Classifier: Programming Language :: Python :: 3
Classifier: Programming Language :: Python :: 3.10
Classifier: Programming Language :: Python :: 3.11
Classifier: Programming Language :: Python :: 3.12
Classifier: Programming Language :: Python :: 3.7
Classifier: Programming Language :: Python :: 3.8
Classifier: Programming Language :: Python :: 3.9
Classifier: Programming Language :: Python :: Implementation :: CPython
Classifier: Topic :: Internet :: WWW/HTTP
Classifier: Topic :: Software Development :: Libraries :: Application Frameworks
Classifier: Topic :: Software Development :: Libraries :: Python Modules
Requires-Dist: aiohttp<4.0.0,>=3.0.0
Requires-Dist: asyncio_atexit<2.0.0,>=1.0.0
Provides-Extra: pydantic
Requires-Dist: pydantic<3.0.0,>=2.0.0; extra == "pydantic"
Provides-Extra: xml
Requires-Dist: xmltodict<1.0.0,>=0.9.2; extra == "xml"
